pyrail_uk/NationalRail.py
pyrail_uk/__init__.py
pyrail_uk/api/__init__.py
pyrail_uk/api/client.py
pyrail_uk/api/departures.py
pyrail_uk/api/referencedata.py
pyrail_uk/api/types.py
pyrail_uk/api/url.py
pyrail_uk/clients/DepartureBoard.py
pyrail_uk/clients/ReferenceData.py
pyrail_uk/clients/__init__.py
pyrail_uk/core/__init__.py
pyrail_uk/core/exceptions.py
pyrail_uk/service/__init__.py
pyrail_uk/service/departures.py
pyrail_uk/service/stations.py
pyrail_uk/service/types.py
pyrail_uk/utils/__init__.py
pyrail_uk/utils/array.py
tests/pyrail_uk/__init__.py
tests/pyrail_uk/api/__init__.py
tests/pyrail_uk/api/test_url.py
tests/pyrail_uk/service/__init__.py
tests/pyrail_uk/service/test_departures.py
tests/pyrail_uk/service/test_departures_integration.py
tests/pyrail_uk/service/test_stations.py
tests/pyrail_uk/service/testutils.py
pyrail_uk-0.2.0.dist-info/METADATA
pyrail_uk-0.2.0.dist-info/WHEEL
pyrail_uk-0.2.0.dist-info/top_level.txt
pyrail_uk-0.2.0.dist-info/RECORD
