Metadata-Version: 2.4
Name: pyrail-uk
Version: 0.2.0
Summary: Python SDK for dealing with the National Rail API
Author-email: Christopher Khoo <khoojinnwei@gmail.com>
License: MIT
Project-URL: repository, https://github.com/thekhoo/pyrail-uk
Classifier: Programming Language :: Python :: 3
Classifier: License :: OSI Approved :: MIT License
Classifier: Operating System :: OS Independent
Requires-Python: >=3.11
Requires-Dist: requests
Requires-Dist: cachetools
Requires-Dist: deprecation
Provides-Extra: development
Requires-Dist: pytest; extra == "development"
Requires-Dist: pytest-sugar; extra == "development"
Requires-Dist: pyrefly; extra == "development"
Requires-Dist: ruff; extra == "development"
Requires-Dist: black; extra == "development"
Requires-Dist: isort; extra == "development"
Provides-Extra: local
Requires-Dist: boto3; extra == "local"
Requires-Dist: boto3-stubs[ssm]; extra == "local"
Requires-Dist: python-dotenv; extra == "local"
Provides-Extra: deploy
Requires-Dist: build; extra == "deploy"
Requires-Dist: twine; extra == "deploy"
